Metadata-Version: 2.1
Name: MatQQv1
Version: 0.0
Summary: MatQQv1
Home-page: UNKNOWN
Author-email: aryatahlil@yahoo.com
License: UNKNOWN
Platform: UNKNOWN
Requires-Python: >=3.6, <3.12
